imio/__init__.py
imio/load.py
imio/save.py
imio/utils.py
imio-0.3.1.dist-info/LICENSE
imio-0.3.1.dist-info/METADATA
imio-0.3.1.dist-info/WHEEL
imio-0.3.1.dist-info/top_level.txt
imio-0.3.1.dist-info/RECORD
