Metadata-Version: 2.1
Name: imio
Version: 0.3.1
Summary: Loading and saving of image data.
Author-email: "Charly Rousseau, Adam Tyson" <code@adamltyson.com>
Project-URL: Homepage, https://github.com/brainglobe/imio
Classifier: Development Status :: 3 - Alpha
Classifier: Intended Audience :: Developers
Classifier: Intended Audience :: Science/Research
Classifier: Operating System :: OS Independent
Classifier: Programming Language :: Python
Classifier: Programming Language :: Python :: 3.8
Classifier: Programming Language :: Python :: 3.9
Classifier: Programming Language :: Python :: 3.10
Classifier: Programming Language :: Python :: 3.11
Requires-Python: >=3.8
License-File: LICENSE
Requires-Dist: brainglobe-utils[slurmio]
Requires-Dist: natsort
Requires-Dist: nibabel
Requires-Dist: nibabel >=2.1.0
Requires-Dist: numpy
Requires-Dist: psutil
Requires-Dist: pyarrow
Requires-Dist: pynrrd
Requires-Dist: scikit-image
Requires-Dist: tifffile
Requires-Dist: tqdm
Provides-Extra: dev
Requires-Dist: black ; extra == 'dev'
Requires-Dist: pre-commit ; extra == 'dev'
Requires-Dist: pytest ; extra == 'dev'
Requires-Dist: pytest-cov ; extra == 'dev'
